modelarium/__init__.py
modelarium-0.0.1.dist-info/licenses/LICENSE
modelarium-0.0.1.dist-info/METADATA
modelarium-0.0.1.dist-info/WHEEL
modelarium-0.0.1.dist-info/top_level.txt
modelarium-0.0.1.dist-info/RECORD
