Metadata-Version: 2.4
Name: modelarium
Version: 0.0.1
Summary: Python wrapper for the Modelarium Java agent-based modelling framework.
Author: Joshua McDonagh
License: MIT License
Project-URL: Homepage, https://github.com/JoshMcDonagh/Modelarium-for-Python
Project-URL: Source, https://github.com/JoshMcDonagh/Modelarium-for-Python
Keywords: agent-based-modeling,simulation,abm,java
Classifier: Development Status :: 1 - Planning
Classifier: Intended Audience :: Science/Research
Classifier: License :: OSI Approved :: MIT License
Classifier: Programming Language :: Python :: 3
Classifier: Topic :: Scientific/Engineering
Requires-Python: >=3.9
License-File: LICENSE
Dynamic: license-file
